django_static_url-0.1.0.dist-info/DESCRIPTION.rst
django_static_url-0.1.0.dist-info/METADATA
django_static_url-0.1.0.dist-info/RECORD
django_static_url-0.1.0.dist-info/WHEEL
django_static_url-0.1.0.dist-info/metadata.json
django_static_url-0.1.0.dist-info/top_level.txt
django_static_url_helper/__init__.py
django_static_url_helper/admin.py
django_static_url_helper/apps.py
django_static_url_helper/django_url_helper.py
django_static_url_helper/models.py
django_static_url_helper/url_helper.py
django_static_url_helper/views.py
django_static_url_helper/migrations/__init__.py
tests/__init__.py
tests/manage.py
tests/test_app/__init__.py
tests/test_app/urls.py
tests/test_app/tests/__init__.py
tests/test_app/tests/test_url_helper.py
tests/test_project/__init__.py
tests/test_project/circleci_settings.py
tests/test_project/settings.py
tests/test_project/urls.py
tests/test_project/wsgi.py
