Metadata-Version: 2.0
Name: django-static-url
Version: 0.1.0
Summary: Dynamically generates new static URLs to invalidate browsers' cache
Home-page: https://github.com/resulto/django-static-url
Author: Resulto Dev Team
Author-email: dev@resulto.ca
License: New BSD
Keywords: django staticfiles
Platform: UNKNOWN
Classifier: Development Status :: 5 - Production/Stable
Classifier: Intended Audience :: Developers
Classifier: Topic :: Software Development :: Libraries :: Python Modules
Classifier: License :: OSI Approved :: BSD License
Classifier: Programming Language :: Python :: 3
Classifier: Programming Language :: Python :: 3.4
Classifier: Programming Language :: Python :: 3.5
Requires-Dist: Django (>=1.8)
